doc484/__init__.py
doc484/__main__.py
doc484/compat.py
doc484/formats.py
doc484/transforms.py
doc484/fixes/__init__.py
doc484/fixes/fix_type_comments.py
doc484/parsers/__init__.py
doc484/parsers/other.py
doc484/parsers/rest.py
doc484-0.3.5.dist-info/LICENSE.txt
doc484-0.3.5.dist-info/METADATA
doc484-0.3.5.dist-info/WHEEL
doc484-0.3.5.dist-info/entry_points.txt
doc484-0.3.5.dist-info/top_level.txt
doc484-0.3.5.dist-info/RECORD
