Metadata-Version: 2.1
Name: doc484
Version: 0.3.5
Summary: Generate PEP 484 type comments from docstrings
Home-page: https://github.com/chadrik/doc484
Author: Chad Dombrova
License: MIT
Keywords: mypy,typing,pep484,docstrings,annotations
Platform: UNKNOWN
Classifier: Development Status :: 4 - Beta
Classifier: Intended Audience :: Developers
Classifier: Topic :: Software Development :: Build Tools
Classifier: License :: OSI Approved :: MIT License
Classifier: Programming Language :: Python :: 2
Classifier: Programming Language :: Python :: 2.7
Classifier: Programming Language :: Python :: 3
Classifier: Programming Language :: Python :: 3.6
Classifier: Programming Language :: Python :: 3.7
Requires-Dist: docutils
Provides-Extra: tests
Requires-Dist: coverage ; extra == 'tests'
Requires-Dist: pytest (==3.6.2) ; extra == 'tests'
Requires-Dist: tox (==2.7.0) ; extra == 'tests'
